[{"iob":0.545,"activity":0.0069,"bolussnooze":0.191,"basaliob":-0.143,"netbasalinsulin":0.05,"hightempinsulin":0.8,"time":"2016-06-27T04:22:27.000Z"},{"iob":0.46,"activity":0.0071,"bolussnooze":0.129,"basaliob":-0.197,"netbasalinsulin":-0.05,"hightempinsulin":0.75,"time":"2016-06-27T04:27:27.000Z"},{"iob":0.373,"activity":0.0073,"bolussnooze":0.078,"basaliob":-0.249,"netbasalinsulin":-0.15,"hightempinsulin":0.7,"time":"2016-06-27T04:32:27.000Z"},{"iob":0.286,"activity":0.0075,"bolussnooze":0.04,"basaliob":-0.3,"netbasalinsulin":-0.2,"hightempinsulin":0.7,"time":"2016-06-27T04:37:27.000Z"},{"iob":0.199,"activity":0.0072,"bolussnooze":0.014,"basaliob":-0.348,"netbasalinsulin":-0.2,"hightempinsulin":0.7,"time":"2016-06-27T04:42:27.000Z"},{"iob":0.166,"activity":0.0067,"bolussnooze":0.002,"basaliob":-0.344,"netbasalinsulin":-0.15,"hightempinsulin":0.7,"time":"2016-06-27T04:47:27.000Z"},{"iob":0.084,"activity":0.0063,"bolussnooze":0,"basaliob":-0.389,"netbasalinsulin":-0.15,"hightempinsulin":0.7,"time":"2016-06-27T04:52:27.000Z"},{"iob":0.005,"activity":0.0058,"bolussnooze":0,"basaliob":-0.432,"netbasalinsulin":-0.2,"hightempinsulin":0.7,"time":"2016-06-27T04:57:27.000Z"},{"iob":-0.072,"activity":0.0053,"bolussnooze":0,"basaliob":-0.472,"netbasalinsulin":-0.2,"hightempinsulin":0.7,"time":"2016-06-27T05:02:27.000Z"},{"iob":-0.095,"activity":0.0048,"bolussnooze":0,"basaliob":-0.46,"netbasalinsulin":-0.15,"hightempinsulin":0.7,"time":"2016-06-27T05:07:27.000Z"},{"iob":-0.117,"activity":0.0042,"bolussnooze":0,"basaliob":-0.446,"netbasalinsulin":-0.1,"hightempinsulin":0.7,"time":"2016-06-27T05:12:27.000Z"},{"iob":-0.135,"activity":0.0036,"bolussnooze":0,"basaliob":-0.429,"netbasalinsulin":-0.1,"hightempinsulin":0.7,"time":"2016-06-27T05:17:27.000Z"},{"iob":-0.149,"activity":0.0029,"bolussnooze":0,"basaliob":-0.409,"netbasalinsulin":-0.15,"hightempinsulin":0.65,"time":"2016-06-27T05:22:27.000Z"},{"iob":-0.159,"activity":0.002,"bolussnooze":0,"basaliob":-0.387,"netbasalinsulin":-0.2,"hightempinsulin":0.6,"time":"2016-06-27T05:27:27.000Z"},{"iob":-0.165,"activity":0.0011,"bolussnooze":0,"basaliob":-0.363,"netbasalinsulin":-0.3,"hightempinsulin":0.5,"time":"2016-06-27T05:32:27.000Z"},{"iob":-0.167,"activity":0.0004,"bolussnooze":0,"basaliob":-0.338,"netbasalinsulin":-0.4,"hightempinsulin":0.4,"time":"2016-06-27T05:37:27.000Z"},{"iob":-0.166,"activity":-0.0002,"bolussnooze":0,"basaliob":-0.312,"netbasalinsulin":-0.55,"hightempinsulin":0.25,"time":"2016-06-27T05:42:27.000Z"},{"iob":-0.163,"activity":-0.0007,"bolussnooze":0,"basaliob":-0.286,"netbasalinsulin":-0.65,"hightempinsulin":0.15,"time":"2016-06-27T05:47:27.000Z"},{"iob":-0.157,"activity":-0.0011,"bolussnooze":0,"basaliob":-0.26,"netbasalinsulin":-0.7,"hightempinsulin":0.1,"time":"2016-06-27T05:52:27.000Z"},{"iob":-0.151,"activity":-0.0014,"bolussnooze":0,"basaliob":-0.235,"netbasalinsulin":-0.75,"hightempinsulin":0.05,"time":"2016-06-27T05:57:27.000Z"},{"iob":-0.142,"activity":-0.0016,"bolussnooze":0,"basaliob":-0.21,"netbasalinsulin":-0.75,"hightempinsulin":0.05,"time":"2016-06-27T06:02:27.000Z"},{"iob":-0.133,"activity":-0.0018,"bolussnooze":0,"basaliob":-0.188,"netbasalinsulin":-0.75,"hightempinsulin":0.05,"time":"2016-06-27T06:07:27.000Z"},{"iob":-0.124,"activity":-0.002,"bolussnooze":0,"basaliob":-0.166,"netbasalinsulin":-0.7,"hightempinsulin":0.05,"time":"2016-06-27T06:12:27.000Z"},{"iob":-0.113,"activity":-0.0021,"bolussnooze":0,"basaliob":-0.146,"netbasalinsulin":-0.65,"hightempinsulin":0.05,"time":"2016-06-27T06:17:27.000Z"},{"iob":-0.102,"activity":-0.0022,"bolussnooze":0,"basaliob":-0.128,"netbasalinsulin":-0.6,"hightempinsulin":0.05,"time":"2016-06-27T06:22:27.000Z"},{"iob":-0.091,"activity":-0.0021,"bolussnooze":0,"basaliob":-0.111,"netbasalinsulin":-0.55,"hightempinsulin":0.05,"time":"2016-06-27T06:27:27.000Z"},{"iob":-0.081,"activity":-0.002,"bolussnooze":0,"basaliob":-0.096,"netbasalinsulin":-0.5,"hightempinsulin":0.05,"time":"2016-06-27T06:32:27.000Z"},{"iob":-0.071,"activity":-0.0019,"bolussnooze":0,"basaliob":-0.082,"netbasalinsulin":-0.45,"hightempinsulin":0.05,"time":"2016-06-27T06:37:27.000Z"},{"iob":-0.062,"activity":-0.0018,"bolussnooze":0,"basaliob":-0.069,"netbasalinsulin":-0.45,"hightempinsulin":0.05,"time":"2016-06-27T06:42:27.000Z"},{"iob":-0.053,"activity":-0.0018,"bolussnooze":0,"basaliob":-0.057,"netbasalinsulin":-0.45,"hightempinsulin":0.05,"time":"2016-06-27T06:47:27.000Z"},{"iob":-0.045,"activity":-0.0017,"bolussnooze":0,"basaliob":-0.047,"netbasalinsulin":-0.45,"hightempinsulin":0.05,"time":"2016-06-27T06:52:27.000Z"},{"iob":-0.037,"activity":-0.0016,"bolussnooze":0,"basaliob":-0.037,"netbasalinsulin":-0.45,"hightempinsulin":0.05,"time":"2016-06-27T06:57:27.000Z"},{"iob":-0.029,"activity":-0.0015,"bolussnooze":0,"basaliob":-0.029,"netbasalinsulin":-0.45,"hightempinsulin":0.05,"time":"2016-06-27T07:02:27.000Z"},{"iob":-0.022,"activity":-0.0014,"bolussnooze":0,"basaliob":-0.022,"netbasalinsulin":-0.45,"hightempinsulin":0,"time":"2016-06-27T07:07:27.000Z"},{"iob":-0.017,"activity":-0.0011,"bolussnooze":0,"basaliob":-0.017,"netbasalinsulin":-0.4,"hightempinsulin":0,"time":"2016-06-27T07:12:27.000Z"},{"iob":-0.012,"activity":-0.0009,"bolussnooze":0,"basaliob":-0.012,"netbasalinsulin":-0.4,"hightempinsulin":0,"time":"2016-06-27T07:17:27.000Z"}]
