[{"iob":1.545,"activity":0.0112,"bolussnooze":0,"basaliob":1.541,"netbasalinsulin":2.3,"hightempinsulin":2.3,"time":"2016-06-19T15:55:35.000Z"},{"iob":1.535,"activity":0.0121,"bolussnooze":0,"basaliob":1.533,"netbasalinsulin":2.3,"hightempinsulin":2.3,"time":"2016-06-19T16:00:35.000Z"},{"iob":1.47,"activity":0.0129,"bolussnooze":0,"basaliob":1.47,"netbasalinsulin":2.2,"hightempinsulin":2.2,"time":"2016-06-19T16:05:35.000Z"},{"iob":1.402,"activity":0.0137,"bolussnooze":0,"basaliob":1.402,"netbasalinsulin":2.1,"hightempinsulin":2.1,"time":"2016-06-19T16:10:35.000Z"},{"iob":1.33,"activity":0.0143,"bolussnooze":0,"basaliob":1.33,"netbasalinsulin":2.05,"hightempinsulin":2.05,"time":"2016-06-19T16:15:35.000Z"},{"iob":1.255,"activity":0.015,"bolussnooze":0,"basaliob":1.255,"netbasalinsulin":1.95,"hightempinsulin":1.95,"time":"2016-06-19T16:20:35.000Z"},{"iob":1.177,"activity":0.0155,"bolussnooze":0,"basaliob":1.177,"netbasalinsulin":1.95,"hightempinsulin":1.95,"time":"2016-06-19T16:25:35.000Z"},{"iob":1.098,"activity":0.0159,"bolussnooze":0,"basaliob":1.098,"netbasalinsulin":1.95,"hightempinsulin":1.95,"time":"2016-06-19T16:30:35.000Z"},{"iob":1.017,"activity":0.0161,"bolussnooze":0,"basaliob":1.017,"netbasalinsulin":1.95,"hightempinsulin":1.95,"time":"2016-06-19T16:35:35.000Z"},{"iob":0.936,"activity":0.0162,"bolussnooze":0,"basaliob":0.936,"netbasalinsulin":1.95,"hightempinsulin":1.95,"time":"2016-06-19T16:40:35.000Z"},{"iob":0.856,"activity":0.0161,"bolussnooze":0,"basaliob":0.856,"netbasalinsulin":1.95,"hightempinsulin":1.95,"time":"2016-06-19T16:45:35.000Z"},{"iob":0.777,"activity":0.0159,"bolussnooze":0,"basaliob":0.777,"netbasalinsulin":1.9,"hightempinsulin":1.9,"time":"2016-06-19T16:50:35.000Z"},{"iob":0.699,"activity":0.0155,"bolussnooze":0,"basaliob":0.699,"netbasalinsulin":1.9,"hightempinsulin":1.9,"time":"2016-06-19T16:55:35.000Z"},{"iob":0.624,"activity":0.0149,"bolussnooze":0,"basaliob":0.624,"netbasalinsulin":1.9,"hightempinsulin":1.9,"time":"2016-06-19T17:00:35.000Z"},{"iob":0.553,"activity":0.0143,"bolussnooze":0,"basaliob":0.553,"netbasalinsulin":1.85,"hightempinsulin":1.85,"time":"2016-06-19T17:05:35.000Z"},{"iob":0.486,"activity":0.0134,"bolussnooze":0,"basaliob":0.486,"netbasalinsulin":1.85,"hightempinsulin":1.85,"time":"2016-06-19T17:10:35.000Z"},{"iob":0.423,"activity":0.0125,"bolussnooze":0,"basaliob":0.423,"netbasalinsulin":1.8,"hightempinsulin":1.8,"time":"2016-06-19T17:15:35.000Z"},{"iob":0.365,"activity":0.0115,"bolussnooze":0,"basaliob":0.365,"netbasalinsulin":1.8,"hightempinsulin":1.8,"time":"2016-06-19T17:20:35.000Z"},{"iob":0.313,"activity":0.0106,"bolussnooze":0,"basaliob":0.313,"netbasalinsulin":1.8,"hightempinsulin":1.8,"time":"2016-06-19T17:25:35.000Z"},{"iob":0.264,"activity":0.0096,"bolussnooze":0,"basaliob":0.264,"netbasalinsulin":1.8,"hightempinsulin":1.8,"time":"2016-06-19T17:30:35.000Z"},{"iob":0.221,"activity":0.0087,"bolussnooze":0,"basaliob":0.221,"netbasalinsulin":1.8,"hightempinsulin":1.8,"time":"2016-06-19T17:35:35.000Z"},{"iob":0.182,"activity":0.0078,"bolussnooze":0,"basaliob":0.182,"netbasalinsulin":1.75,"hightempinsulin":1.75,"time":"2016-06-19T17:40:35.000Z"},{"iob":0.148,"activity":0.0068,"bolussnooze":0,"basaliob":0.148,"netbasalinsulin":1.75,"hightempinsulin":1.75,"time":"2016-06-19T17:45:35.000Z"},{"iob":0.118,"activity":0.0059,"bolussnooze":0,"basaliob":0.118,"netbasalinsulin":1.65,"hightempinsulin":1.65,"time":"2016-06-19T17:50:35.000Z"},{"iob":0.093,"activity":0.0051,"bolussnooze":0,"basaliob":0.093,"netbasalinsulin":1.55,"hightempinsulin":1.55,"time":"2016-06-19T17:55:35.000Z"},{"iob":0.072,"activity":0.0043,"bolussnooze":0,"basaliob":0.072,"netbasalinsulin":1.4,"hightempinsulin":1.4,"time":"2016-06-19T18:00:35.000Z"},{"iob":0.054,"activity":0.0036,"bolussnooze":0,"basaliob":0.054,"netbasalinsulin":1.3,"hightempinsulin":1.3,"time":"2016-06-19T18:05:35.000Z"},{"iob":0.039,"activity":0.0029,"bolussnooze":0,"basaliob":0.039,"netbasalinsulin":1.15,"hightempinsulin":1.15,"time":"2016-06-19T18:10:35.000Z"},{"iob":0.027,"activity":0.0023,"bolussnooze":0,"basaliob":0.027,"netbasalinsulin":1.05,"hightempinsulin":1.05,"time":"2016-06-19T18:15:35.000Z"},{"iob":0.018,"activity":0.0018,"bolussnooze":0,"basaliob":0.018,"netbasalinsulin":0.9,"hightempinsulin":0.9,"time":"2016-06-19T18:20:35.000Z"},{"iob":0.011,"activity":0.0014,"bolussnooze":0,"basaliob":0.011,"netbasalinsulin":0.8,"hightempinsulin":0.8,"time":"2016-06-19T18:25:35.000Z"},{"iob":0.006,"activity":0.001,"bolussnooze":0,"basaliob":0.006,"netbasalinsulin":0.7,"hightempinsulin":0.7,"time":"2016-06-19T18:30:35.000Z"},{"iob":0.003,"activity":0.0007,"bolussnooze":0,"basaliob":0.003,"netbasalinsulin":0.55,"hightempinsulin":0.55,"time":"2016-06-19T18:35:35.000Z"},{"iob":0.001,"activity":0.0004,"bolussnooze":0,"basaliob":0.001,"netbasalinsulin":0.45,"hightempinsulin":0.45,"time":"2016-06-19T18:40:35.000Z"},{"iob":0,"activity":0.0002,"bolussnooze":0,"basaliob":0,"netbasalinsulin":0.3,"hightempinsulin":0.3,"time":"2016-06-19T18:45:35.000Z"},{"iob":0,"activity":0.0001,"bolussnooze":0,"basaliob":0,"netbasalinsulin":0.2,"hightempinsulin":0.2,"time":"2016-06-19T18:50:35.000Z"}]
