[{"iob":-0.267,"activity":-0.002,"bolussnooze":0,"basaliob":-0.269,"netbasalinsulin":-0.4,"hightempinsulin":0.6,"time":"2016-06-22T07:58:12.000Z"},{"iob":-0.306,"activity":-0.0021,"bolussnooze":0,"basaliob":-0.307,"netbasalinsulin":-0.35,"hightempinsulin":0.6,"time":"2016-06-22T08:03:12.000Z"},{"iob":-0.345,"activity":-0.0023,"bolussnooze":0,"basaliob":-0.345,"netbasalinsulin":-0.35,"hightempinsulin":0.6,"time":"2016-06-22T08:08:12.000Z"},{"iob":-0.382,"activity":-0.0025,"bolussnooze":0,"basaliob":-0.382,"netbasalinsulin":-0.35,"hightempinsulin":0.6,"time":"2016-06-22T08:13:12.000Z"},{"iob":-0.419,"activity":-0.0027,"bolussnooze":0,"basaliob":-0.419,"netbasalinsulin":-0.45,"hightempinsulin":0.55,"time":"2016-06-22T08:18:12.000Z"},{"iob":-0.454,"activity":-0.0029,"bolussnooze":0,"basaliob":-0.454,"netbasalinsulin":-0.6,"hightempinsulin":0.45,"time":"2016-06-22T08:23:12.000Z"},{"iob":-0.439,"activity":-0.003,"bolussnooze":0,"basaliob":-0.439,"netbasalinsulin":-0.65,"hightempinsulin":0.4,"time":"2016-06-22T08:28:12.000Z"},{"iob":-0.423,"activity":-0.0033,"bolussnooze":0,"basaliob":-0.423,"netbasalinsulin":-0.75,"hightempinsulin":0.3,"time":"2016-06-22T08:33:12.000Z"},{"iob":-0.405,"activity":-0.0035,"bolussnooze":0,"basaliob":-0.405,"netbasalinsulin":-0.85,"hightempinsulin":0.2,"time":"2016-06-22T08:38:12.000Z"},{"iob":-0.387,"activity":-0.0036,"bolussnooze":0,"basaliob":-0.387,"netbasalinsulin":-0.85,"hightempinsulin":0.15,"time":"2016-06-22T08:43:12.000Z"},{"iob":-0.368,"activity":-0.0038,"bolussnooze":0,"basaliob":-0.368,"netbasalinsulin":-0.85,"hightempinsulin":0.15,"time":"2016-06-22T08:48:12.000Z"},{"iob":-0.348,"activity":-0.004,"bolussnooze":0,"basaliob":-0.348,"netbasalinsulin":-0.85,"hightempinsulin":0.15,"time":"2016-06-22T08:53:12.000Z"},{"iob":-0.327,"activity":-0.0042,"bolussnooze":0,"basaliob":-0.327,"netbasalinsulin":-0.85,"hightempinsulin":0.15,"time":"2016-06-22T08:58:12.000Z"},{"iob":-0.306,"activity":-0.0043,"bolussnooze":0,"basaliob":-0.306,"netbasalinsulin":-0.8,"hightempinsulin":0.15,"time":"2016-06-22T09:03:12.000Z"},{"iob":-0.284,"activity":-0.0043,"bolussnooze":0,"basaliob":-0.284,"netbasalinsulin":-0.7,"hightempinsulin":0.15,"time":"2016-06-22T09:08:12.000Z"},{"iob":-0.263,"activity":-0.0043,"bolussnooze":0,"basaliob":-0.263,"netbasalinsulin":-0.65,"hightempinsulin":0.15,"time":"2016-06-22T09:13:12.000Z"},{"iob":-0.241,"activity":-0.0043,"bolussnooze":0,"basaliob":-0.241,"netbasalinsulin":-0.6,"hightempinsulin":0.15,"time":"2016-06-22T09:18:12.000Z"},{"iob":-0.22,"activity":-0.0042,"bolussnooze":0,"basaliob":-0.22,"netbasalinsulin":-0.55,"hightempinsulin":0.15,"time":"2016-06-22T09:23:12.000Z"},{"iob":-0.199,"activity":-0.0041,"bolussnooze":0,"basaliob":-0.199,"netbasalinsulin":-0.45,"hightempinsulin":0.15,"time":"2016-06-22T09:28:12.000Z"},{"iob":-0.18,"activity":-0.004,"bolussnooze":0,"basaliob":-0.18,"netbasalinsulin":-0.4,"hightempinsulin":0.15,"time":"2016-06-22T09:33:12.000Z"},{"iob":-0.161,"activity":-0.0038,"bolussnooze":0,"basaliob":-0.161,"netbasalinsulin":-0.35,"hightempinsulin":0.15,"time":"2016-06-22T09:38:12.000Z"},{"iob":-0.143,"activity":-0.0036,"bolussnooze":0,"basaliob":-0.143,"netbasalinsulin":-0.35,"hightempinsulin":0.15,"time":"2016-06-22T09:43:12.000Z"},{"iob":-0.126,"activity":-0.0034,"bolussnooze":0,"basaliob":-0.126,"netbasalinsulin":-0.35,"hightempinsulin":0.15,"time":"2016-06-22T09:48:12.000Z"},{"iob":-0.11,"activity":-0.0032,"bolussnooze":0,"basaliob":-0.11,"netbasalinsulin":-0.35,"hightempinsulin":0.15,"time":"2016-06-22T09:53:12.000Z"},{"iob":-0.095,"activity":-0.003,"bolussnooze":0,"basaliob":-0.095,"netbasalinsulin":-0.35,"hightempinsulin":0.15,"time":"2016-06-22T09:58:12.000Z"},{"iob":-0.08,"activity":-0.0028,"bolussnooze":0,"basaliob":-0.08,"netbasalinsulin":-0.35,"hightempinsulin":0.15,"time":"2016-06-22T10:03:12.000Z"},{"iob":-0.067,"activity":-0.0027,"bolussnooze":0,"basaliob":-0.067,"netbasalinsulin":-0.35,"hightempinsulin":0.15,"time":"2016-06-22T10:08:12.000Z"},{"iob":-0.055,"activity":-0.0025,"bolussnooze":0,"basaliob":-0.055,"netbasalinsulin":-0.45,"hightempinsulin":0.05,"time":"2016-06-22T10:13:12.000Z"},{"iob":-0.044,"activity":-0.0022,"bolussnooze":0,"basaliob":-0.044,"netbasalinsulin":-0.5,"hightempinsulin":0,"time":"2016-06-22T10:18:12.000Z"},{"iob":-0.034,"activity":-0.0019,"bolussnooze":0,"basaliob":-0.034,"netbasalinsulin":-0.5,"hightempinsulin":0,"time":"2016-06-22T10:23:12.000Z"},{"iob":-0.026,"activity":-0.0017,"bolussnooze":0,"basaliob":-0.026,"netbasalinsulin":-0.5,"hightempinsulin":0,"time":"2016-06-22T10:28:12.000Z"},{"iob":-0.019,"activity":-0.0014,"bolussnooze":0,"basaliob":-0.019,"netbasalinsulin":-0.5,"hightempinsulin":0,"time":"2016-06-22T10:33:12.000Z"},{"iob":-0.013,"activity":-0.0011,"bolussnooze":0,"basaliob":-0.013,"netbasalinsulin":-0.5,"hightempinsulin":0,"time":"2016-06-22T10:38:12.000Z"},{"iob":-0.009,"activity":-0.0009,"bolussnooze":0,"basaliob":-0.009,"netbasalinsulin":-0.45,"hightempinsulin":0,"time":"2016-06-22T10:43:12.000Z"},{"iob":-0.006,"activity":-0.0007,"bolussnooze":0,"basaliob":-0.006,"netbasalinsulin":-0.4,"hightempinsulin":0,"time":"2016-06-22T10:48:12.000Z"},{"iob":-0.003,"activity":-0.0005,"bolussnooze":0,"basaliob":-0.003,"netbasalinsulin":-0.3,"hightempinsulin":0,"time":"2016-06-22T10:53:12.000Z"}]
