{
  "bg": 171, 
  "temp": "absolute", 
  "snoozeBG": 114, 
  "recieved": true, 
  "predBGs": {
    "IOB": [
      171, 
      170, 
      169, 
      167, 
      166, 
      165, 
      163, 
      161, 
      159, 
      157, 
      154, 
      151, 
      148, 
      145, 
      141, 
      138, 
      134, 
      131, 
      128, 
      125, 
      122, 
      119, 
      117, 
      115, 
      112, 
      111, 
      109, 
      107, 
      106, 
      105, 
      104, 
      104, 
      103, 
      103, 
      103, 
      102
    ]
  }, 
  "rate": 0.2, 
  "reason": "COB: 0, Dev: 6, BGI: -1.98, ISF: 89.9, Target: 122; Eventual BG 114<122, Snooze BG 114, setting 0.21U/hr", 
  "COB": 0, 
  "eventualBG": 114, 
  "timestamp": "2016-06-24T12:55:28.434153", 
  "duration": 30, 
  "tick": -1, 
  "IOB": 0.704
}