{
  "bg": 105, 
  "temp": "absolute", 
  "snoozeBG": 121, 
  "recieved": true, 
  "predBGs": {
    "COB": [
      105, 
      105, 
      106, 
      107, 
      109, 
      111, 
      113, 
      116, 
      118, 
      121, 
      123, 
      125, 
      127, 
      129, 
      131, 
      133, 
      134, 
      135, 
      137, 
      137, 
      138, 
      139, 
      139, 
      140, 
      141, 
      141, 
      142, 
      142, 
      143, 
      143, 
      143, 
      144, 
      144, 
      144, 
      144, 
      144, 
      145
    ], 
    "aCOB": [
      105, 
      110, 
      114, 
      118, 
      121, 
      125, 
      127, 
      129, 
      131, 
      132, 
      132, 
      132, 
      132, 
      132, 
      132, 
      133, 
      133, 
      134, 
      134, 
      135, 
      136, 
      136, 
      137, 
      138, 
      138, 
      139, 
      139, 
      140, 
      140, 
      140, 
      141, 
      141, 
      141, 
      142
    ], 
    "IOB": [
      105, 
      105, 
      106, 
      106, 
      107, 
      108, 
      110, 
      111, 
      112, 
      113, 
      114, 
      114, 
      115, 
      115, 
      115, 
      115, 
      116, 
      117, 
      117, 
      118, 
      119, 
      119, 
      120, 
      121, 
      121, 
      122, 
      122, 
      123, 
      123, 
      123, 
      124, 
      124, 
      124, 
      124, 
      125
    ]
  }, 
  "rate": 1.1, 
  "reason": "COB: 12, Dev: 30, BGI: -4.3, ISF: 66.1, Target: 105; Eventual BG 145>=105, temp 0<1.094U/hr", 
  "COB": 12, 
  "eventualBG": 145, 
  "timestamp": "2016-06-19T20:16:26.521549", 
  "duration": 30, 
  "tick": "+3", 
  "IOB": 0.246
}