{
  "device": "openaps://indy-e1", 
  "pump": {
    "battery": {
      "status": "normal", 
      "voltage": 1.42
    }, 
    "status": {
      "status": "normal", 
      "timestamp": "2016-06-21T07:05:51.000Z", 
      "bolusing": false, 
      "suspended": false
    }, 
    "reservoir": 94.3, 
    "clock": "2016-06-21T00:05:24-07:00"
  }, 
  "openaps": {
    "suggested": {
      "bg": 139, 
      "temp": "absolute", 
      "snoozeBG": 109, 
      "timestamp": "2016-06-21T07:07:12.000Z", 
      "predBGs": {
        "COB": [
          139, 
          136, 
          131, 
          127, 
          123, 
          119, 
          116, 
          114, 
          112, 
          110, 
          109, 
          109, 
          109, 
          109, 
          110, 
          112, 
          114, 
          116, 
          119, 
          122, 
          125, 
          128, 
          132, 
          137, 
          141, 
          145, 
          149, 
          153, 
          157, 
          160, 
          163, 
          166, 
          169, 
          172, 
          175, 
          177, 
          180
        ], 
        "aCOB": [
          139, 
          140, 
          140, 
          140, 
          139, 
          139, 
          140, 
          140, 
          141, 
          142, 
          144, 
          146, 
          148, 
          150, 
          153, 
          156, 
          159, 
          162, 
          166, 
          169, 
          173, 
          176, 
          180, 
          184, 
          188, 
          191, 
          194, 
          197, 
          199, 
          201, 
          202, 
          203, 
          204, 
          204, 
          204, 
          205
        ], 
        "IOB": [
          139, 
          135, 
          130, 
          125, 
          119, 
          114, 
          109, 
          104, 
          99, 
          94, 
          89, 
          85, 
          81, 
          77, 
          74, 
          72, 
          70, 
          68, 
          67, 
          66, 
          66, 
          66, 
          67, 
          67, 
          69, 
          70, 
          71, 
          71, 
          72, 
          73, 
          73, 
          74, 
          74, 
          75
        ]
      }, 
      "rate": 0.85, 
      "reason": "COB: 37, Dev: 32, BGI: -8.64, ISF: 70.8, Target: 109; Eventual BG 180>=109, temp 0<0.85U/hr", 
      "COB": 37, 
      "eventualBG": 180, 
      "duration": 30, 
      "tick": -3, 
      "IOB": 1.392
    }, 
    "iob": [
      {
        "netbasalinsulin": -0.65, 
        "activity": 0.0244, 
        "basaliob": -0.216, 
        "time": "2016-06-21T07:05:24.000Z", 
        "hightempinsulin": 0.35, 
        "bolussnooze": 0, 
        "iob": 1.392
      }, 
      {
        "netbasalinsulin": -0.65, 
        "activity": 0.0263, 
        "basaliob": -0.264, 
        "time": "2016-06-21T07:10:24.000Z", 
        "hightempinsulin": 0.35, 
        "bolussnooze": 0, 
        "iob": 1.21
      }, 
      {
        "netbasalinsulin": -0.65, 
        "activity": 0.0269, 
        "basaliob": -0.313, 
        "time": "2016-06-21T07:15:24.000Z", 
        "hightempinsulin": 0.35, 
        "bolussnooze": 0, 
        "iob": 1.024
      }, 
      {
        "netbasalinsulin": -0.6, 
        "activity": 0.0254, 
        "basaliob": -0.36, 
        "time": "2016-06-21T07:20:24.000Z", 
        "hightempinsulin": 0.35, 
        "bolussnooze": 0, 
        "iob": 0.847
      }, 
      {
        "netbasalinsulin": -0.65, 
        "activity": 0.0239, 
        "basaliob": -0.406, 
        "time": "2016-06-21T07:25:24.000Z", 
        "hightempinsulin": 0.35, 
        "bolussnooze": 0, 
        "iob": 0.678
      }, 
      {
        "netbasalinsulin": -0.6, 
        "activity": 0.0222, 
        "basaliob": -0.401, 
        "time": "2016-06-21T07:30:24.000Z", 
        "hightempinsulin": 0.35, 
        "bolussnooze": 0, 
        "iob": 0.566
      }, 
      {
        "netbasalinsulin": -0.5, 
        "activity": 0.0206, 
        "basaliob": -0.394, 
        "time": "2016-06-21T07:35:24.000Z", 
        "hightempinsulin": 0.35, 
        "bolussnooze": 0, 
        "iob": 0.464
      }, 
      {
        "netbasalinsulin": -0.45, 
        "activity": 0.0188, 
        "basaliob": -0.385, 
        "time": "2016-06-21T07:40:24.000Z", 
        "hightempinsulin": 0.35, 
        "bolussnooze": 0, 
        "iob": 0.37
      }, 
      {
        "netbasalinsulin": -0.4, 
        "activity": 0.0171, 
        "basaliob": -0.373, 
        "time": "2016-06-21T07:45:24.000Z", 
        "hightempinsulin": 0.35, 
        "bolussnooze": 0, 
        "iob": 0.284
      }, 
      {
        "netbasalinsulin": -0.35, 
        "activity": 0.0154, 
        "basaliob": -0.36, 
        "time": "2016-06-21T07:50:24.000Z", 
        "hightempinsulin": 0.35, 
        "bolussnooze": 0, 
        "iob": 0.207
      }, 
      {
        "netbasalinsulin": -0.3, 
        "activity": 0.0136, 
        "basaliob": -0.345, 
        "time": "2016-06-21T07:55:24.000Z", 
        "hightempinsulin": 0.35, 
        "bolussnooze": 0, 
        "iob": 0.139
      }, 
      {
        "netbasalinsulin": -0.3, 
        "activity": 0.0119, 
        "basaliob": -0.328, 
        "time": "2016-06-21T08:00:24.000Z", 
        "hightempinsulin": 0.35, 
        "bolussnooze": 0, 
        "iob": 0.08
      }, 
      {
        "netbasalinsulin": -0.3, 
        "activity": 0.0103, 
        "basaliob": -0.309, 
        "time": "2016-06-21T08:05:24.000Z", 
        "hightempinsulin": 0.35, 
        "bolussnooze": 0, 
        "iob": 0.028
      }, 
      {
        "netbasalinsulin": -0.3, 
        "activity": 0.0087, 
        "basaliob": -0.289, 
        "time": "2016-06-21T08:10:24.000Z", 
        "hightempinsulin": 0.35, 
        "bolussnooze": 0, 
        "iob": -0.015
      }, 
      {
        "netbasalinsulin": -0.35, 
        "activity": 0.0071, 
        "basaliob": -0.267, 
        "time": "2016-06-21T08:15:24.000Z", 
        "hightempinsulin": 0.3, 
        "bolussnooze": 0, 
        "iob": -0.051
      }, 
      {
        "netbasalinsulin": -0.4, 
        "activity": 0.0057, 
        "basaliob": -0.246, 
        "time": "2016-06-21T08:20:24.000Z", 
        "hightempinsulin": 0.25, 
        "bolussnooze": 0, 
        "iob": -0.079
      }, 
      {
        "netbasalinsulin": -0.45, 
        "activity": 0.0044, 
        "basaliob": -0.224, 
        "time": "2016-06-21T08:25:24.000Z", 
        "hightempinsulin": 0.2, 
        "bolussnooze": 0, 
        "iob": -0.101
      }, 
      {
        "netbasalinsulin": -0.45, 
        "activity": 0.0031, 
        "basaliob": -0.202, 
        "time": "2016-06-21T08:30:24.000Z", 
        "hightempinsulin": 0.2, 
        "bolussnooze": 0, 
        "iob": -0.116
      }, 
      {
        "netbasalinsulin": -0.45, 
        "activity": 0.002, 
        "basaliob": -0.181, 
        "time": "2016-06-21T08:35:24.000Z", 
        "hightempinsulin": 0.2, 
        "bolussnooze": 0, 
        "iob": -0.126
      }, 
      {
        "netbasalinsulin": -0.35, 
        "activity": 0.0008, 
        "basaliob": -0.162, 
        "time": "2016-06-21T08:40:24.000Z", 
        "hightempinsulin": 0.2, 
        "bolussnooze": 0, 
        "iob": -0.13
      }, 
      {
        "netbasalinsulin": -0.35, 
        "activity": -0.0003, 
        "basaliob": -0.143, 
        "time": "2016-06-21T08:45:24.000Z", 
        "hightempinsulin": 0.2, 
        "bolussnooze": 0, 
        "iob": -0.129
      }, 
      {
        "netbasalinsulin": -0.35, 
        "activity": -0.0014, 
        "basaliob": -0.125, 
        "time": "2016-06-21T08:50:24.000Z", 
        "hightempinsulin": 0.2, 
        "bolussnooze": 0, 
        "iob": -0.122
      }, 
      {
        "netbasalinsulin": -0.4, 
        "activity": -0.0025, 
        "basaliob": -0.108, 
        "time": "2016-06-21T08:55:24.000Z", 
        "hightempinsulin": 0.15, 
        "bolussnooze": 0, 
        "iob": -0.109
      }, 
      {
        "netbasalinsulin": -0.45, 
        "activity": -0.0031, 
        "basaliob": -0.093, 
        "time": "2016-06-21T09:00:24.000Z", 
        "hightempinsulin": 0.1, 
        "bolussnooze": 0, 
        "iob": -0.093
      }, 
      {
        "netbasalinsulin": -0.45, 
        "activity": -0.0029, 
        "basaliob": -0.078, 
        "time": "2016-06-21T09:05:24.000Z", 
        "hightempinsulin": 0.1, 
        "bolussnooze": 0, 
        "iob": -0.078
      }, 
      {
        "netbasalinsulin": -0.5, 
        "activity": -0.0026, 
        "basaliob": -0.065, 
        "time": "2016-06-21T09:10:24.000Z", 
        "hightempinsulin": 0.05, 
        "bolussnooze": 0, 
        "iob": -0.065
      }, 
      {
        "netbasalinsulin": -0.5, 
        "activity": -0.0024, 
        "basaliob": -0.053, 
        "time": "2016-06-21T09:15:24.000Z", 
        "hightempinsulin": 0.05, 
        "bolussnooze": 0, 
        "iob": -0.053
      }, 
      {
        "netbasalinsulin": -0.5, 
        "activity": -0.0021, 
        "basaliob": -0.042, 
        "time": "2016-06-21T09:20:24.000Z", 
        "hightempinsulin": 0.05, 
        "bolussnooze": 0, 
        "iob": -0.042
      }, 
      {
        "netbasalinsulin": -0.55, 
        "activity": -0.0018, 
        "basaliob": -0.033, 
        "time": "2016-06-21T09:25:24.000Z", 
        "hightempinsulin": 0, 
        "bolussnooze": 0, 
        "iob": -0.033
      }, 
      {
        "netbasalinsulin": -0.5, 
        "activity": -0.0016, 
        "basaliob": -0.025, 
        "time": "2016-06-21T09:30:24.000Z", 
        "hightempinsulin": 0, 
        "bolussnooze": 0, 
        "iob": -0.025
      }, 
      {
        "netbasalinsulin": -0.45, 
        "activity": -0.0013, 
        "basaliob": -0.019, 
        "time": "2016-06-21T09:35:24.000Z", 
        "hightempinsulin": 0, 
        "bolussnooze": 0, 
        "iob": -0.019
      }, 
      {
        "netbasalinsulin": -0.45, 
        "activity": -0.0011, 
        "basaliob": -0.013, 
        "time": "2016-06-21T09:40:24.000Z", 
        "hightempinsulin": 0, 
        "bolussnooze": 0, 
        "iob": -0.013
      }, 
      {
        "netbasalinsulin": -0.4, 
        "activity": -0.0009, 
        "basaliob": -0.009, 
        "time": "2016-06-21T09:45:24.000Z", 
        "hightempinsulin": 0, 
        "bolussnooze": 0, 
        "iob": -0.009
      }, 
      {
        "netbasalinsulin": -0.35, 
        "activity": -0.0007, 
        "basaliob": -0.006, 
        "time": "2016-06-21T09:50:24.000Z", 
        "hightempinsulin": 0, 
        "bolussnooze": 0, 
        "iob": -0.006
      }, 
      {
        "netbasalinsulin": -0.35, 
        "activity": -0.0005, 
        "basaliob": -0.003, 
        "time": "2016-06-21T09:55:24.000Z", 
        "hightempinsulin": 0, 
        "bolussnooze": 0, 
        "iob": -0.003
      }, 
      {
        "netbasalinsulin": -0.25, 
        "activity": -0.0003, 
        "basaliob": -0.002, 
        "time": "2016-06-21T10:00:24.000Z", 
        "hightempinsulin": 0, 
        "bolussnooze": 0, 
        "iob": -0.002
      }
    ], 
    "enacted": {
      "bg": 139, 
      "temp": "absolute", 
      "snoozeBG": 109, 
      "recieved": true, 
      "predBGs": {
        "COB": [
          139, 
          136, 
          131, 
          127, 
          123, 
          119, 
          116, 
          114, 
          112, 
          110, 
          109, 
          109, 
          109, 
          109, 
          110, 
          112, 
          114, 
          116, 
          119, 
          122, 
          125, 
          128, 
          132, 
          137, 
          141, 
          145, 
          149, 
          153, 
          157, 
          160, 
          163, 
          166, 
          169, 
          172, 
          175, 
          177, 
          180
        ], 
        "aCOB": [
          139, 
          140, 
          140, 
          140, 
          139, 
          139, 
          140, 
          140, 
          141, 
          142, 
          144, 
          146, 
          148, 
          150, 
          153, 
          156, 
          159, 
          162, 
          166, 
          169, 
          173, 
          176, 
          180, 
          184, 
          188, 
          191, 
          194, 
          197, 
          199, 
          201, 
          202, 
          203, 
          204, 
          204, 
          204, 
          205
        ], 
        "IOB": [
          139, 
          135, 
          130, 
          125, 
          119, 
          114, 
          109, 
          104, 
          99, 
          94, 
          89, 
          85, 
          81, 
          77, 
          74, 
          72, 
          70, 
          68, 
          67, 
          66, 
          66, 
          66, 
          67, 
          67, 
          69, 
          70, 
          71, 
          71, 
          72, 
          73, 
          73, 
          74, 
          74, 
          75
        ]
      }, 
      "reason": "COB: 37, Dev: 32, BGI: -8.64, ISF: 70.8, Target: 109; Eventual BG 180>=109, temp 0<0.85U/hr", 
      "rate": 0.85, 
      "COB": 37, 
      "eventualBG": 180, 
      "timestamp": "2016-06-21T07:07:18.000Z", 
      "duration": 30, 
      "tick": -3, 
      "IOB": 1.392
    }
  }, 
  "mmtune": {
    "scanDetails": [
      [
        "916.564", 
        5, 
        -76
      ], 
      [
        "916.588", 
        5, 
        -63
      ], 
      [
        "916.612", 
        5, 
        -74
      ], 
      [
        "916.636", 
        5, 
        -68
      ], 
      [
        "916.660", 
        3, 
        -89
      ], 
      [
        "916.684", 
        3, 
        -93
      ]
    ], 
    "setFreq": 916.588, 
    "timestamp": "2016-06-21T07:05:39.000Z", 
    "usedDefault": false
  }
}