{
  "device": "openaps://indy-e1", 
  "pump": {
    "battery": {
      "status": "normal", 
      "voltage": 1.57
    }, 
    "status": {
      "status": "normal", 
      "timestamp": "2016-06-29T01:24:48.000Z", 
      "bolusing": false, 
      "suspended": false
    }, 
    "reservoir": 120.375, 
    "clock": "2016-06-28T18:24:15-07:00"
  }, 
  "openaps": {
    "suggested": {
      "bg": 126, 
      "temp": "absolute", 
      "snoozeBG": 49, 
      "timestamp": "2016-06-29T01:27:14.000Z", 
      "predBGs": {
        "COB": [
          126, 
          125, 
          123, 
          120, 
          116, 
          112, 
          107, 
          101, 
          94, 
          88, 
          82, 
          77, 
          72, 
          67, 
          63, 
          59, 
          56, 
          53, 
          51, 
          50, 
          49, 
          49, 
          49, 
          50, 
          51, 
          52, 
          54, 
          57, 
          60, 
          63, 
          67, 
          70, 
          73, 
          77, 
          80, 
          84, 
          87
        ], 
        "aCOB": [
          126, 
          131, 
          134, 
          137, 
          139, 
          140, 
          139, 
          138, 
          137, 
          135, 
          134, 
          133, 
          132, 
          132, 
          132, 
          132, 
          133, 
          134, 
          135, 
          137, 
          140, 
          143, 
          146, 
          149, 
          153, 
          158, 
          162, 
          167, 
          172, 
          178, 
          183, 
          188, 
          194, 
          199, 
          204, 
          208, 
          213
        ], 
        "IOB": [
          126, 
          125, 
          122, 
          118, 
          113, 
          107, 
          100, 
          92, 
          83, 
          74, 
          65, 
          56, 
          47, 
          39
        ]
      }, 
      "reason": "COB: 64, Dev: 25, BGI: -5.12, ISF: 80, Target: 115; Eventual BG 87<115, setting -2.8U/hr, but 28m left and 0 ~ req 0U/hr: no action required", 
      "COB": 64, 
      "eventualBG": 87, 
      "tick": "+3", 
      "IOB": 2.247
    }, 
    "iob": [
      {
        "netbasalinsulin": -0.3, 
        "activity": 0.0128, 
        "basaliob": 0.028, 
        "time": "2016-06-29T01:24:15.000Z", 
        "hightempinsulin": 0.35, 
        "bolussnooze": 0.461, 
        "iob": 2.247
      }, 
      {
        "netbasalinsulin": -0.35, 
        "activity": 0.015, 
        "basaliob": -0.023, 
        "time": "2016-06-29T01:29:15.000Z", 
        "hightempinsulin": 0.35, 
        "bolussnooze": 0.313, 
        "iob": 2.122
      }, 
      {
        "netbasalinsulin": -0.35, 
        "activity": 0.0171, 
        "basaliob": -0.026, 
        "time": "2016-06-29T01:34:15.000Z", 
        "hightempinsulin": 0.35, 
        "bolussnooze": 0.195, 
        "iob": 2.036
      }, 
      {
        "netbasalinsulin": -0.4, 
        "activity": 0.0192, 
        "basaliob": -0.079, 
        "time": "2016-06-29T01:39:15.000Z", 
        "hightempinsulin": 0.35, 
        "bolussnooze": 0.105, 
        "iob": 1.89
      }, 
      {
        "netbasalinsulin": -0.4, 
        "activity": 0.0212, 
        "basaliob": -0.134, 
        "time": "2016-06-29T01:44:15.000Z", 
        "hightempinsulin": 0.35, 
        "bolussnooze": 0.043, 
        "iob": 1.735
      }, 
      {
        "netbasalinsulin": -0.4, 
        "activity": 0.023, 
        "basaliob": -0.188, 
        "time": "2016-06-29T01:49:15.000Z", 
        "hightempinsulin": 0.35, 
        "bolussnooze": 0.008, 
        "iob": 1.569
      }, 
      {
        "netbasalinsulin": -0.35, 
        "activity": 0.0248, 
        "basaliob": -0.192, 
        "time": "2016-06-29T01:54:15.000Z", 
        "hightempinsulin": 0.35, 
        "bolussnooze": 0, 
        "iob": 1.445
      }, 
      {
        "netbasalinsulin": -0.35, 
        "activity": 0.0257, 
        "basaliob": -0.195, 
        "time": "2016-06-29T01:59:15.000Z", 
        "hightempinsulin": 0.35, 
        "bolussnooze": 0, 
        "iob": 1.316
      }, 
      {
        "netbasalinsulin": -0.3, 
        "activity": 0.0249, 
        "basaliob": -0.196, 
        "time": "2016-06-29T02:04:15.000Z", 
        "hightempinsulin": 0.35, 
        "bolussnooze": 0, 
        "iob": 1.191
      }, 
      {
        "netbasalinsulin": -0.3, 
        "activity": 0.0241, 
        "basaliob": -0.196, 
        "time": "2016-06-29T02:09:15.000Z", 
        "hightempinsulin": 0.35, 
        "bolussnooze": 0, 
        "iob": 1.071
      }, 
      {
        "netbasalinsulin": -0.3, 
        "activity": 0.0233, 
        "basaliob": -0.195, 
        "time": "2016-06-29T02:14:15.000Z", 
        "hightempinsulin": 0.35, 
        "bolussnooze": 0, 
        "iob": 0.954
      }, 
      {
        "netbasalinsulin": -0.25, 
        "activity": 0.0225, 
        "basaliob": -0.192, 
        "time": "2016-06-29T02:19:15.000Z", 
        "hightempinsulin": 0.35, 
        "bolussnooze": 0, 
        "iob": 0.842
      }, 
      {
        "netbasalinsulin": -0.2, 
        "activity": 0.0216, 
        "basaliob": -0.187, 
        "time": "2016-06-29T02:24:15.000Z", 
        "hightempinsulin": 0.35, 
        "bolussnooze": 0, 
        "iob": 0.733
      }, 
      {
        "netbasalinsulin": -0.2, 
        "activity": 0.02, 
        "basaliob": -0.181, 
        "time": "2016-06-29T02:29:15.000Z", 
        "hightempinsulin": 0.35, 
        "bolussnooze": 0, 
        "iob": 0.633
      }, 
      {
        "netbasalinsulin": -0.15, 
        "activity": 0.0185, 
        "basaliob": -0.174, 
        "time": "2016-06-29T02:34:15.000Z", 
        "hightempinsulin": 0.35, 
        "bolussnooze": 0, 
        "iob": 0.541
      }, 
      {
        "netbasalinsulin": -0.1, 
        "activity": 0.0169, 
        "basaliob": -0.166, 
        "time": "2016-06-29T02:39:15.000Z", 
        "hightempinsulin": 0.35, 
        "bolussnooze": 0, 
        "iob": 0.456
      }, 
      {
        "netbasalinsulin": -0.1, 
        "activity": 0.0154, 
        "basaliob": -0.157, 
        "time": "2016-06-29T02:44:15.000Z", 
        "hightempinsulin": 0.35, 
        "bolussnooze": 0, 
        "iob": 0.379
      }, 
      {
        "netbasalinsulin": -0.05, 
        "activity": 0.0139, 
        "basaliob": -0.147, 
        "time": "2016-06-29T02:49:15.000Z", 
        "hightempinsulin": 0.35, 
        "bolussnooze": 0, 
        "iob": 0.31
      }, 
      {
        "netbasalinsulin": 0, 
        "activity": 0.0125, 
        "basaliob": -0.136, 
        "time": "2016-06-29T02:54:15.000Z", 
        "hightempinsulin": 0.35, 
        "bolussnooze": 0, 
        "iob": 0.247
      }, 
      {
        "netbasalinsulin": 0, 
        "activity": 0.0111, 
        "basaliob": -0.125, 
        "time": "2016-06-29T02:59:15.000Z", 
        "hightempinsulin": 0.35, 
        "bolussnooze": 0, 
        "iob": 0.192
      }, 
      {
        "netbasalinsulin": 0, 
        "activity": 0.0097, 
        "basaliob": -0.114, 
        "time": "2016-06-29T03:04:15.000Z", 
        "hightempinsulin": 0.35, 
        "bolussnooze": 0, 
        "iob": 0.143
      }, 
      {
        "netbasalinsulin": -0.05, 
        "activity": 0.0084, 
        "basaliob": -0.103, 
        "time": "2016-06-29T03:09:15.000Z", 
        "hightempinsulin": 0.3, 
        "bolussnooze": 0, 
        "iob": 0.101
      }, 
      {
        "netbasalinsulin": -0.05, 
        "activity": 0.0071, 
        "basaliob": -0.092, 
        "time": "2016-06-29T03:14:15.000Z", 
        "hightempinsulin": 0.3, 
        "bolussnooze": 0, 
        "iob": 0.066
      }, 
      {
        "netbasalinsulin": -0.1, 
        "activity": 0.0058, 
        "basaliob": -0.081, 
        "time": "2016-06-29T03:19:15.000Z", 
        "hightempinsulin": 0.25, 
        "bolussnooze": 0, 
        "iob": 0.036
      }, 
      {
        "netbasalinsulin": -0.1, 
        "activity": 0.0046, 
        "basaliob": -0.071, 
        "time": "2016-06-29T03:24:15.000Z", 
        "hightempinsulin": 0.25, 
        "bolussnooze": 0, 
        "iob": 0.014
      }, 
      {
        "netbasalinsulin": -0.15, 
        "activity": 0.0033, 
        "basaliob": -0.061, 
        "time": "2016-06-29T03:29:15.000Z", 
        "hightempinsulin": 0.2, 
        "bolussnooze": 0, 
        "iob": -0.003
      }, 
      {
        "netbasalinsulin": -0.2, 
        "activity": 0.0021, 
        "basaliob": -0.051, 
        "time": "2016-06-29T03:34:15.000Z", 
        "hightempinsulin": 0.15, 
        "bolussnooze": 0, 
        "iob": -0.013
      }, 
      {
        "netbasalinsulin": -0.3, 
        "activity": 0.0009, 
        "basaliob": -0.042, 
        "time": "2016-06-29T03:39:15.000Z", 
        "hightempinsulin": 0.05, 
        "bolussnooze": 0, 
        "iob": -0.018
      }, 
      {
        "netbasalinsulin": -0.35, 
        "activity": 0.0001, 
        "basaliob": -0.034, 
        "time": "2016-06-29T03:44:15.000Z", 
        "hightempinsulin": 0, 
        "bolussnooze": 0, 
        "iob": -0.018
      }, 
      {
        "netbasalinsulin": -0.35, 
        "activity": -0.0001, 
        "basaliob": -0.027, 
        "time": "2016-06-29T03:49:15.000Z", 
        "hightempinsulin": 0, 
        "bolussnooze": 0, 
        "iob": -0.017
      }, 
      {
        "netbasalinsulin": -0.35, 
        "activity": -0.0003, 
        "basaliob": -0.021, 
        "time": "2016-06-29T03:54:15.000Z", 
        "hightempinsulin": 0, 
        "bolussnooze": 0, 
        "iob": -0.016
      }, 
      {
        "netbasalinsulin": -0.35, 
        "activity": -0.0004, 
        "basaliob": -0.016, 
        "time": "2016-06-29T03:59:15.000Z", 
        "hightempinsulin": 0, 
        "bolussnooze": 0, 
        "iob": -0.014
      }, 
      {
        "netbasalinsulin": -0.35, 
        "activity": -0.0006, 
        "basaliob": -0.011, 
        "time": "2016-06-29T04:04:15.000Z", 
        "hightempinsulin": 0, 
        "bolussnooze": 0, 
        "iob": -0.011
      }, 
      {
        "netbasalinsulin": -0.3, 
        "activity": -0.0007, 
        "basaliob": -0.008, 
        "time": "2016-06-29T04:09:15.000Z", 
        "hightempinsulin": 0, 
        "bolussnooze": 0, 
        "iob": -0.008
      }, 
      {
        "netbasalinsulin": -0.3, 
        "activity": -0.0005, 
        "basaliob": -0.005, 
        "time": "2016-06-29T04:14:15.000Z", 
        "hightempinsulin": 0, 
        "bolussnooze": 0, 
        "iob": -0.005
      }, 
      {
        "netbasalinsulin": -0.25, 
        "activity": -0.0004, 
        "basaliob": -0.003, 
        "time": "2016-06-29T04:19:15.000Z", 
        "hightempinsulin": 0, 
        "bolussnooze": 0, 
        "iob": -0.003
      }
    ], 
    "enacted": {
      "bg": 123, 
      "temp": "absolute", 
      "snoozeBG": 19, 
      "recieved": true, 
      "predBGs": {
        "COB": [
          123, 
          121, 
          119, 
          116, 
          112, 
          107, 
          101, 
          95, 
          87, 
          80, 
          73, 
          66, 
          59, 
          53, 
          47, 
          42, 
          39, 
          39, 
          39, 
          39, 
          39, 
          39, 
          39, 
          39, 
          39, 
          39, 
          39, 
          39, 
          39, 
          39, 
          39, 
          39, 
          39, 
          39, 
          39, 
          39, 
          41
        ], 
        "aCOB": [
          123, 
          128, 
          133, 
          136, 
          138, 
          140, 
          140, 
          140, 
          138, 
          137, 
          135, 
          134, 
          132, 
          131, 
          130, 
          130, 
          130, 
          130, 
          131, 
          132, 
          134, 
          136, 
          138, 
          141, 
          144, 
          147, 
          151, 
          155, 
          160, 
          165, 
          170, 
          175, 
          180, 
          185, 
          189, 
          194, 
          199
        ], 
        "IOB": [
          123, 
          121, 
          118, 
          114, 
          109, 
          103, 
          96, 
          88, 
          79, 
          69, 
          60, 
          50, 
          41, 
          39
        ]
      }, 
      "reason": "COB: 64, Dev: 5, BGI: -4.56, ISF: 80, Target: 115; Eventual BG 41<115, setting -4.3U/hr", 
      "rate": 0, 
      "COB": 64, 
      "eventualBG": 41, 
      "timestamp": "2016-06-29T01:22:40.000Z", 
      "duration": 30, 
      "tick": -1, 
      "IOB": 2.297
    }
  }, 
  "mmtune": {
    "scanDetails": [
      [
        "916.564", 
        1, 
        -98
      ], 
      [
        "916.588", 
        4, 
        -79
      ], 
      [
        "916.612", 
        5, 
        -67
      ], 
      [
        "916.636", 
        5, 
        -62
      ], 
      [
        "916.660", 
        5, 
        -61
      ], 
      [
        "916.684", 
        5, 
        -62
      ], 
      [
        "916.708", 
        5, 
        -64
      ]
    ], 
    "setFreq": 916.66, 
    "timestamp": "2016-06-29T01:24:28.000Z", 
    "usedDefault": false
  }
}