{
  "device": "openaps://indy-e1", 
  "pump": {
    "battery": {
      "status": "normal", 
      "voltage": 1.4
    }, 
    "status": {
      "status": "normal", 
      "timestamp": "2016-06-22T19:51:48.000Z", 
      "bolusing": false, 
      "suspended": false
    }, 
    "reservoir": 67.95, 
    "clock": "2016-06-22T12:51:13-07:00"
  }, 
  "openaps": {
    "enacted": {
      "bg": 121, 
      "temp": "absolute", 
      "snoozeBG": 114, 
      "recieved": true, 
      "predBGs": {
        "IOB": [
          121, 
          118, 
          115, 
          113, 
          111, 
          109, 
          107, 
          106, 
          105, 
          104, 
          104, 
          103, 
          104, 
          104, 
          105, 
          105, 
          105, 
          106, 
          106, 
          106, 
          106, 
          107, 
          107, 
          107, 
          107, 
          107, 
          108
        ]
      }, 
      "reason": "COB: 0, Dev: 0, BGI: -2.31, ISF: 94.1, Target: 125; Eventual BG 114<125, setting -0.038U/hr", 
      "rate": 0, 
      "COB": 0, 
      "eventualBG": 114, 
      "timestamp": "2016-06-22T19:47:45.000Z", 
      "duration": 30, 
      "tick": -3, 
      "IOB": 0.07
    }
  }, 
  "mmtune": {
    "scanDetails": [
      [
        "916.564", 
        5, 
        -80
      ], 
      [
        "916.588", 
        5, 
        -67
      ], 
      [
        "916.612", 
        5, 
        -64
      ], 
      [
        "916.636", 
        5, 
        -63
      ], 
      [
        "916.660", 
        5, 
        -62
      ], 
      [
        "916.684", 
        5, 
        -65
      ], 
      [
        "916.708", 
        5, 
        -68
      ]
    ], 
    "setFreq": 916.66, 
    "timestamp": "2016-06-22T19:51:27.000Z", 
    "usedDefault": false
  }
}