{
  "device": "openaps://indy-e1", 
  "pump": {
    "battery": {
      "status": "normal", 
      "voltage": 1.57
    }, 
    "status": {
      "status": "normal", 
      "timestamp": "2016-06-29T08:20:49.000Z", 
      "bolusing": false, 
      "suspended": false
    }, 
    "reservoir": 110.525, 
    "clock": "2016-06-29T01:20:24-07:00"
  }, 
  "openaps": {
    "suggested": {
      "bg": 87, 
      "temp": "absolute", 
      "snoozeBG": 108, 
      "timestamp": "2016-06-29T08:22:10.000Z", 
      "predBGs": {
        "COB": [
          87, 
          83, 
          81, 
          80, 
          80, 
          82, 
          85, 
          89, 
          94, 
          100, 
          107, 
          114, 
          122, 
          131, 
          140, 
          149, 
          159, 
          170, 
          180, 
          191, 
          201, 
          211, 
          220, 
          229, 
          237, 
          245, 
          253, 
          260, 
          266, 
          272, 
          278, 
          284, 
          289, 
          294, 
          298, 
          302, 
          306
        ], 
        "aCOB": [
          87, 
          83, 
          80, 
          79, 
          79, 
          80, 
          83, 
          86, 
          92, 
          97, 
          104, 
          111, 
          119, 
          127, 
          136, 
          145, 
          155, 
          165, 
          176, 
          186, 
          196, 
          206, 
          215, 
          224, 
          232, 
          240, 
          247, 
          254, 
          261, 
          267, 
          273, 
          278, 
          283, 
          288, 
          293, 
          297, 
          301
        ], 
        "IOB": [
          87, 
          83, 
          79, 
          76, 
          73, 
          72, 
          70, 
          70, 
          70, 
          70, 
          70, 
          69, 
          69, 
          70, 
          71, 
          73, 
          75, 
          78, 
          82, 
          86, 
          89, 
          92, 
          95, 
          98, 
          100, 
          102, 
          104, 
          106, 
          107, 
          108, 
          109, 
          110, 
          111, 
          111, 
          112
        ]
      }, 
      "rate": 0, 
      "reason": "COB: 41, Dev: 62, BGI: -13.72, ISF: 114.3, Target: 139; BG 87<94.5", 
      "COB": 41, 
      "eventualBG": 306, 
      "duration": 30, 
      "tick": -3, 
      "IOB": 0.359
    }, 
    "iob": [
      {
        "netbasalinsulin": -1.55, 
        "activity": 0.024, 
        "basaliob": -0.647, 
        "time": "2016-06-29T08:20:24.000Z", 
        "hightempinsulin": 0.35, 
        "bolussnooze": 0, 
        "iob": 0.359
      }, 
      {
        "netbasalinsulin": -1.55, 
        "activity": 0.0217, 
        "basaliob": -0.67, 
        "time": "2016-06-29T08:25:24.000Z", 
        "hightempinsulin": 0.35, 
        "bolussnooze": 0, 
        "iob": 0.201
      }, 
      {
        "netbasalinsulin": -1.55, 
        "activity": 0.0191, 
        "basaliob": -0.691, 
        "time": "2016-06-29T08:30:24.000Z", 
        "hightempinsulin": 0.35, 
        "bolussnooze": 0, 
        "iob": 0.055
      }, 
      {
        "netbasalinsulin": -1.5, 
        "activity": 0.0165, 
        "basaliob": -0.71, 
        "time": "2016-06-29T08:35:24.000Z", 
        "hightempinsulin": 0.35, 
        "bolussnooze": 0, 
        "iob": -0.077
      }, 
      {
        "netbasalinsulin": -1.5, 
        "activity": 0.0138, 
        "basaliob": -0.728, 
        "time": "2016-06-29T08:40:24.000Z", 
        "hightempinsulin": 0.35, 
        "bolussnooze": 0, 
        "iob": -0.196
      }, 
      {
        "netbasalinsulin": -1.45, 
        "activity": 0.0112, 
        "basaliob": -0.694, 
        "time": "2016-06-29T08:45:24.000Z", 
        "hightempinsulin": 0.35, 
        "bolussnooze": 0, 
        "iob": -0.252
      }, 
      {
        "netbasalinsulin": -1.4, 
        "activity": 0.0087, 
        "basaliob": -0.659, 
        "time": "2016-06-29T08:50:24.000Z", 
        "hightempinsulin": 0.35, 
        "bolussnooze": 0, 
        "iob": -0.296
      }, 
      {
        "netbasalinsulin": -1.3, 
        "activity": 0.0062, 
        "basaliob": -0.623, 
        "time": "2016-06-29T08:55:24.000Z", 
        "hightempinsulin": 0.35, 
        "bolussnooze": 0, 
        "iob": -0.327
      }, 
      {
        "netbasalinsulin": -1.25, 
        "activity": 0.0046, 
        "basaliob": -0.587, 
        "time": "2016-06-29T09:00:24.000Z", 
        "hightempinsulin": 0.35, 
        "bolussnooze": 0, 
        "iob": -0.349
      }, 
      {
        "netbasalinsulin": -1.2, 
        "activity": 0.0032, 
        "basaliob": -0.55, 
        "time": "2016-06-29T09:05:24.000Z", 
        "hightempinsulin": 0.35, 
        "bolussnooze": 0, 
        "iob": -0.365
      }, 
      {
        "netbasalinsulin": -1.15, 
        "activity": 0.0018, 
        "basaliob": -0.513, 
        "time": "2016-06-29T09:10:24.000Z", 
        "hightempinsulin": 0.35, 
        "bolussnooze": 0, 
        "iob": -0.374
      }, 
      {
        "netbasalinsulin": -1.05, 
        "activity": 0.0005, 
        "basaliob": -0.476, 
        "time": "2016-06-29T09:15:24.000Z", 
        "hightempinsulin": 0.35, 
        "bolussnooze": 0, 
        "iob": -0.377
      }, 
      {
        "netbasalinsulin": -1, 
        "activity": -0.0008, 
        "basaliob": -0.439, 
        "time": "2016-06-29T09:20:24.000Z", 
        "hightempinsulin": 0.35, 
        "bolussnooze": 0, 
        "iob": -0.373
      }, 
      {
        "netbasalinsulin": -0.95, 
        "activity": -0.002, 
        "basaliob": -0.402, 
        "time": "2016-06-29T09:25:24.000Z", 
        "hightempinsulin": 0.35, 
        "bolussnooze": 0, 
        "iob": -0.363
      }, 
      {
        "netbasalinsulin": -0.9, 
        "activity": -0.0032, 
        "basaliob": -0.367, 
        "time": "2016-06-29T09:30:24.000Z", 
        "hightempinsulin": 0.35, 
        "bolussnooze": 0, 
        "iob": -0.347
      }, 
      {
        "netbasalinsulin": -0.8, 
        "activity": -0.0044, 
        "basaliob": -0.332, 
        "time": "2016-06-29T09:35:24.000Z", 
        "hightempinsulin": 0.35, 
        "bolussnooze": 0, 
        "iob": -0.325
      }, 
      {
        "netbasalinsulin": -0.75, 
        "activity": -0.0055, 
        "basaliob": -0.297, 
        "time": "2016-06-29T09:40:24.000Z", 
        "hightempinsulin": 0.35, 
        "bolussnooze": 0, 
        "iob": -0.297
      }, 
      {
        "netbasalinsulin": -0.7, 
        "activity": -0.0066, 
        "basaliob": -0.264, 
        "time": "2016-06-29T09:45:24.000Z", 
        "hightempinsulin": 0.35, 
        "bolussnooze": 0, 
        "iob": -0.264
      }, 
      {
        "netbasalinsulin": -0.65, 
        "activity": -0.0063, 
        "basaliob": -0.233, 
        "time": "2016-06-29T09:50:24.000Z", 
        "hightempinsulin": 0.35, 
        "bolussnooze": 0, 
        "iob": -0.233
      }, 
      {
        "netbasalinsulin": -0.65, 
        "activity": -0.006, 
        "basaliob": -0.203, 
        "time": "2016-06-29T09:55:24.000Z", 
        "hightempinsulin": 0.35, 
        "bolussnooze": 0, 
        "iob": -0.203
      }, 
      {
        "netbasalinsulin": -0.7, 
        "activity": -0.0056, 
        "basaliob": -0.175, 
        "time": "2016-06-29T10:00:24.000Z", 
        "hightempinsulin": 0.3, 
        "bolussnooze": 0, 
        "iob": -0.175
      }, 
      {
        "netbasalinsulin": -0.8, 
        "activity": -0.0052, 
        "basaliob": -0.149, 
        "time": "2016-06-29T10:05:24.000Z", 
        "hightempinsulin": 0.2, 
        "bolussnooze": 0, 
        "iob": -0.149
      }, 
      {
        "netbasalinsulin": -0.95, 
        "activity": -0.0047, 
        "basaliob": -0.125, 
        "time": "2016-06-29T10:10:24.000Z", 
        "hightempinsulin": 0.05, 
        "bolussnooze": 0, 
        "iob": -0.125
      }, 
      {
        "netbasalinsulin": -0.95, 
        "activity": -0.0042, 
        "basaliob": -0.104, 
        "time": "2016-06-29T10:15:24.000Z", 
        "hightempinsulin": 0, 
        "bolussnooze": 0, 
        "iob": -0.104
      }, 
      {
        "netbasalinsulin": -0.95, 
        "activity": -0.0037, 
        "basaliob": -0.086, 
        "time": "2016-06-29T10:20:24.000Z", 
        "hightempinsulin": 0, 
        "bolussnooze": 0, 
        "iob": -0.086
      }, 
      {
        "netbasalinsulin": -0.9, 
        "activity": -0.0032, 
        "basaliob": -0.069, 
        "time": "2016-06-29T10:25:24.000Z", 
        "hightempinsulin": 0, 
        "bolussnooze": 0, 
        "iob": -0.069
      }, 
      {
        "netbasalinsulin": -0.8, 
        "activity": -0.0028, 
        "basaliob": -0.055, 
        "time": "2016-06-29T10:30:24.000Z", 
        "hightempinsulin": 0, 
        "bolussnooze": 0, 
        "iob": -0.055
      }, 
      {
        "netbasalinsulin": -0.75, 
        "activity": -0.0024, 
        "basaliob": -0.044, 
        "time": "2016-06-29T10:35:24.000Z", 
        "hightempinsulin": 0, 
        "bolussnooze": 0, 
        "iob": -0.044
      }, 
      {
        "netbasalinsulin": -0.65, 
        "activity": -0.002, 
        "basaliob": -0.034, 
        "time": "2016-06-29T10:40:24.000Z", 
        "hightempinsulin": 0, 
        "bolussnooze": 0, 
        "iob": -0.034
      }, 
      {
        "netbasalinsulin": -0.6, 
        "activity": -0.0017, 
        "basaliob": -0.025, 
        "time": "2016-06-29T10:45:24.000Z", 
        "hightempinsulin": 0, 
        "bolussnooze": 0, 
        "iob": -0.025
      }, 
      {
        "netbasalinsulin": -0.55, 
        "activity": -0.0014, 
        "basaliob": -0.018, 
        "time": "2016-06-29T10:50:24.000Z", 
        "hightempinsulin": 0, 
        "bolussnooze": 0, 
        "iob": -0.018
      }, 
      {
        "netbasalinsulin": -0.5, 
        "activity": -0.0011, 
        "basaliob": -0.013, 
        "time": "2016-06-29T10:55:24.000Z", 
        "hightempinsulin": 0, 
        "bolussnooze": 0, 
        "iob": -0.013
      }, 
      {
        "netbasalinsulin": -0.4, 
        "activity": -0.0009, 
        "basaliob": -0.009, 
        "time": "2016-06-29T11:00:24.000Z", 
        "hightempinsulin": 0, 
        "bolussnooze": 0, 
        "iob": -0.009
      }, 
      {
        "netbasalinsulin": -0.35, 
        "activity": -0.0007, 
        "basaliob": -0.005, 
        "time": "2016-06-29T11:05:24.000Z", 
        "hightempinsulin": 0, 
        "bolussnooze": 0, 
        "iob": -0.005
      }, 
      {
        "netbasalinsulin": -0.3, 
        "activity": -0.0005, 
        "basaliob": -0.003, 
        "time": "2016-06-29T11:10:24.000Z", 
        "hightempinsulin": 0, 
        "bolussnooze": 0, 
        "iob": -0.003
      }, 
      {
        "netbasalinsulin": -0.25, 
        "activity": -0.0003, 
        "basaliob": -0.002, 
        "time": "2016-06-29T11:15:24.000Z", 
        "hightempinsulin": 0, 
        "bolussnooze": 0, 
        "iob": -0.002
      }
    ], 
    "enacted": {
      "requested": {
        "duration": 30, 
        "rate": 0, 
        "temp": "absolute"
      }, 
      "bg": 87, 
      "temp": "absolute", 
      "snoozeBG": 108, 
      "timestamp": "2016-06-29T08:22:22.000Z", 
      "predBGs": {
        "COB": [
          87, 
          83, 
          81, 
          80, 
          80, 
          82, 
          85, 
          89, 
          94, 
          100, 
          107, 
          114, 
          122, 
          131, 
          140, 
          149, 
          159, 
          170, 
          180, 
          191, 
          201, 
          211, 
          220, 
          229, 
          237, 
          245, 
          253, 
          260, 
          266, 
          272, 
          278, 
          284, 
          289, 
          294, 
          298, 
          302, 
          306
        ], 
        "aCOB": [
          87, 
          83, 
          80, 
          79, 
          79, 
          80, 
          83, 
          86, 
          92, 
          97, 
          104, 
          111, 
          119, 
          127, 
          136, 
          145, 
          155, 
          165, 
          176, 
          186, 
          196, 
          206, 
          215, 
          224, 
          232, 
          240, 
          247, 
          254, 
          261, 
          267, 
          273, 
          278, 
          283, 
          288, 
          293, 
          297, 
          301
        ], 
        "IOB": [
          87, 
          83, 
          79, 
          76, 
          73, 
          72, 
          70, 
          70, 
          70, 
          70, 
          70, 
          69, 
          69, 
          70, 
          71, 
          73, 
          75, 
          78, 
          82, 
          86, 
          89, 
          92, 
          95, 
          98, 
          100, 
          102, 
          104, 
          106, 
          107, 
          108, 
          109, 
          110, 
          111, 
          111, 
          112
        ]
      }, 
      "reason": "COB: 41, Dev: 62, BGI: -13.72, ISF: 114.3, Target: 139; BG 87<94.5", 
      "rate": 0, 
      "COB": 41, 
      "eventualBG": 306, 
      "recieved": false, 
      "duration": 19, 
      "tick": -3, 
      "IOB": 0.359
    }
  }, 
  "mmtune": {
    "scanDetails": [
      [
        "916.564", 
        5, 
        -82
      ], 
      [
        "916.588", 
        5, 
        -74
      ], 
      [
        "916.612", 
        5, 
        -66
      ], 
      [
        "916.636", 
        5, 
        -66
      ], 
      [
        "916.660", 
        4, 
        -73
      ], 
      [
        "916.684", 
        5, 
        -67
      ], 
      [
        "916.708", 
        5, 
        -71
      ]
    ], 
    "setFreq": 916.636, 
    "timestamp": "2016-06-29T08:20:28.000Z", 
    "usedDefault": false
  }
}